src/vloerverwarming_monitor_sldewit/__init__.py
src/vloerverwarming_monitor_sldewit/vloerverwarming_monitor.py
vloerverwarmingmonitor_sldewit-0.0.4.dist-info/METADATA
vloerverwarmingmonitor_sldewit-0.0.4.dist-info/WHEEL
vloerverwarmingmonitor_sldewit-0.0.4.dist-info/licenses/LICENSE
vloerverwarmingmonitor_sldewit-0.0.4.dist-info/RECORD
