Metadata-Version: 2.1
Name: VloerverwarmingMonitor_sldewit
Version: 0.0.4
Summary: Monitoring systeem voor vloerverwarming
Project-URL: Homepage, https://github.com/sldewit/VloerverwarmingMonitor
Project-URL: Bug Tracker, https://github.com/sldewit/VloerverwarmingMonitor/issues
Author-email: Stephan de Wit <stephan@de-wit.me>
License-File: LICENSE
Classifier: License :: OSI Approved :: MIT License
Classifier: Operating System :: OS Independent
Classifier: Programming Language :: Python :: 3
Requires-Python: >=3.7
Requires-Dist: paho-mqtt==1.6.1
Requires-Dist: pi1wire==0.3.0
